sphinxnotes/strike/__init__.py
sphinxnotes/strike/meta.py
sphinxnotes/strike/py.typed
sphinxnotes_strike-1.5.dist-info/licenses/LICENSE
sphinxnotes_strike-1.5.dist-info/METADATA
sphinxnotes_strike-1.5.dist-info/WHEEL
sphinxnotes_strike-1.5.dist-info/top_level.txt
sphinxnotes_strike-1.5.dist-info/RECORD
