Metadata-Version: 2.4
Name: sphinxnotes-strike
Version: 1.5
Summary: An extension that adds strikethrough text support to Sphinx
Author: Shengyu Zhang
Maintainer: Shengyu Zhang
License-Expression: BSD-3-Clause
Project-URL: homepage, https://sphinx.silverrainz.me/strike
Project-URL: documentation, https://sphinx.silverrainz.me/strike
Project-URL: repository, https://github.com/sphinx-notes/strike
Project-URL: changelog, https://sphinx.silverrainz.me/strike/changelog.html
Project-URL: tracker, https://github.com/sphinx-notes/strike/issues
Keywords: sphinx,extension,documentation,sphinxnotes
Classifier: Development Status :: 3 - Alpha
Classifier: Environment :: Plugins
Classifier: Framework :: Sphinx
Classifier: Framework :: Sphinx :: Extension
Classifier: Operating System :: OS Independent
Classifier: Programming Language :: Python
Classifier: Programming Language :: Python :: 3
Classifier: Topic :: Documentation
Classifier: Topic :: Documentation :: Sphinx
Requires-Python: >=3.12
License-File: LICENSE
Requires-Dist: Sphinx>=7.0
Provides-Extra: dev
Requires-Dist: build; extra == "dev"
Requires-Dist: twine; extra == "dev"
Requires-Dist: cruft; extra == "dev"
Requires-Dist: ruff>=0.11.10; extra == "dev"
Requires-Dist: pre-commit; extra == "dev"
Provides-Extra: test
Requires-Dist: pytest; extra == "test"
Provides-Extra: docs
Requires-Dist: furo; extra == "docs"
Requires-Dist: sphinx_design; extra == "docs"
Requires-Dist: sphinx_copybutton; extra == "docs"
Requires-Dist: sphinxcontrib-gtagjs; extra == "docs"
Requires-Dist: sphinx-sitemap; extra == "docs"
Requires-Dist: sphinxext-opengraph; extra == "docs"
Requires-Dist: sphinx-last-updated-by-git; extra == "docs"
Requires-Dist: sphinxnotes-project; extra == "docs"
Requires-Dist: sphinxnotes-comboroles; extra == "docs"
Dynamic: license-file
